senzing_typedef/__init__.py
senzing_typedef-0.2.18.dist-info/licenses/LICENSE
senzing_typedef-0.2.18.dist-info/licenses/.github/senzing-corporate-contributor-license-agreement.pdf
senzing_typedef-0.2.18.dist-info/licenses/.github/senzing-individual-contributor-license-agreement.pdf
senzing_typedef-0.2.18.dist-info/METADATA
senzing_typedef-0.2.18.dist-info/WHEEL
senzing_typedef-0.2.18.dist-info/entry_points.txt
senzing_typedef-0.2.18.dist-info/top_level.txt
senzing_typedef-0.2.18.dist-info/RECORD
