Metadata-Version: 2.4
Name: senzing-typedef
Version: 0.2.18
Summary: Helper functions for working with Senzing JSON
Author-email: senzing <support@senzing.com>
License-Expression: Apache-2.0
Project-URL: bugtracker, https://github.com/senzing-garage/sz-sdk-json-type-definition/issues
Project-URL: changelog, https://github.com/senzing-garage/sz-sdk-json-type-definition/blob/main/CHANGELOG.md
Project-URL: source, https://github.com/senzing-garage/sz-sdk-json-type-definition
Classifier: Programming Language :: Python :: 3
Classifier: Operating System :: OS Independent
Requires-Python: >=3.10
License-File: LICENSE
License-File: .github/senzing-corporate-contributor-license-agreement.pdf
License-File: .github/senzing-individual-contributor-license-agreement.pdf
Requires-Dist: senzing==4.0.4
Requires-Dist: senzing-core==1.0.3
Dynamic: license-file
